flask_app_creator/__init__.py
flask_app_creator/base/.env
flask_app_creator/base/.secret.toml
flask_app_creator/base/config.toml
flask_app_creator/base/project_name/__init__.py
flask_app_creator/base/project_name/app.py
flask_app_creator/base/project_name/blueprint/__init__.py
flask_app_creator/base/project_name/blueprint/views.py
flask_app_creator/base/project_name/config.py
flask_app_creator/base/project_name/extensions/__init__.py
flask_app_creator/base/project_name/static/css/style.css
flask_app_creator/base/project_name/templates/base.html
flask_app_creator/base/project_name/views.py
flask_app_creator/base/tests/__init__.py
flask_app_creator/base/tests/conftest.py
flask_app_creator/main.py
flask_app_creator/utils.py
flask_app_creator-0.1.2.dist-info/LICENSE
flask_app_creator-0.1.2.dist-info/METADATA
flask_app_creator-0.1.2.dist-info/WHEEL
flask_app_creator-0.1.2.dist-info/entry_points.txt
flask_app_creator-0.1.2.dist-info/RECORD
